README.rst
setup.py
coolclip/__init__.py
coolclip/__main__.py
coolclip.egg-info/PKG-INFO
coolclip.egg-info/SOURCES.txt
coolclip.egg-info/dependency_links.txt
coolclip.egg-info/not-zip-safe
coolclip.egg-info/requires.txt
coolclip.egg-info/top_level.txt
scripts/coolclip